therm_inv_tools-1.0.9.9.dist-info/licenses/LICENSE
tools/thermal_interacting_tools.py
therm_inv_tools-1.0.9.9.dist-info/METADATA
therm_inv_tools-1.0.9.9.dist-info/WHEEL
therm_inv_tools-1.0.9.9.dist-info/top_level.txt
therm_inv_tools-1.0.9.9.dist-info/RECORD
