Metadata-Version: 2.4
Name: therm_inv_tools
Version: 1.0.9.9
Summary: A package containing all my tools for thermal inversions
Home-page: https://github.com/Anthony904175/therm_inv_tools.git
Author: Anthony R. Osborne
Author-email: anthony.r.osborne019@pm.me
License: MIT
Requires-Python: >=3.8
License-File: LICENSE
Dynamic: author
Dynamic: author-email
Dynamic: description
Dynamic: description-content-type
Dynamic: home-page
Dynamic: license
Dynamic: license-file
Dynamic: requires-python
Dynamic: summary
